mikemazzi/__init__.py
mikemazzi/csvdata.py
mikemazzi/database.py
mikemazzi/functions.py
tests/__init__.py
tests/test.py
mikemazzi-0.0.12.dist-info/METADATA
mikemazzi-0.0.12.dist-info/WHEEL
mikemazzi-0.0.12.dist-info/top_level.txt
mikemazzi-0.0.12.dist-info/RECORD
