Metadata-Version: 2.1
Name: mikemazzi
Version: 0.0.12
Summary: Assignment pipeline
Home-page: https://gitlab.com/mik3sw/2022_assignment1_users_db
Author: Michele Marcucci, Davide Mazzitelli
Author-email: test@email.it
Classifier: Programming Language :: Python :: 3
Classifier: License :: OSI Approved :: MIT License
Classifier: Operating System :: OS Independent
Requires-Python: >=3.7
